SILK2/Tools/usage/__init__.py
SILK2/Tools/usage/__main__.py
SILK2/Tools/usage/get_info.sh
SILK2/Tools/usage/log_usage.py
silk2.tools.usage-1.1.5.dist-info/LICENSE
silk2.tools.usage-1.1.5.dist-info/METADATA
silk2.tools.usage-1.1.5.dist-info/WHEEL
silk2.tools.usage-1.1.5.dist-info/top_level.txt
silk2.tools.usage-1.1.5.dist-info/RECORD
