Metadata-Version: 2.1
Name: silk2.tools.usage
Version: 1.1.5
Summary: Analyze the usage of each hardware resource on SOPHON products.
Home-page: https://github.com/sophgo
Author: zhiju.huang
Author-email: zhiju.huang@sophgo.com
License: BSD
Platform: UNKNOWN
Classifier: Programming Language :: Python :: 3
Classifier: License :: OSI Approved :: BSD License
Classifier: Operating System :: POSIX :: Linux
Requires-Python: >=3.6
Requires-Dist: bs4
Requires-Dist: numpy
Requires-Dist: pyecharts
